h_net_dynamic_chunking/__init__.py
h_net_dynamic_chunking/h_net.py
h_net_dynamic_chunking/h_net_dynamic_chunking.py
h_net_dynamic_chunking/multi_head_h_net_dynamic_chunking.py
h_net_dynamic_chunking-0.3.1.dist-info/licenses/LICENSE
h_net_dynamic_chunking-0.3.1.dist-info/METADATA
h_net_dynamic_chunking-0.3.1.dist-info/WHEEL
h_net_dynamic_chunking-0.3.1.dist-info/top_level.txt
h_net_dynamic_chunking-0.3.1.dist-info/RECORD
