Metadata-Version: 2.4
Name: h-net-dynamic-chunking
Version: 0.3.1
Summary: H-Net Dynamic Chunking Modules
Author-email: Phil Wang <lucidrains@gmail.com>
License-Expression: MIT
Project-URL: Homepage, https://pypi.org/project/h-net-dynamic-chunking/
Project-URL: Repository, https://github.com/lucidrains/h-net-dynamic-chunking
Keywords: artificial intelligence,deep learning,learned chunking,learned tokenization
Classifier: Development Status :: 4 - Beta
Classifier: Intended Audience :: Developers
Classifier: Topic :: Scientific/Engineering :: Artificial Intelligence
Classifier: Programming Language :: Python :: 3.9
Requires-Python: >=3.9
License-File: LICENSE
Requires-Dist: assoc-scan>=0.0.2
Requires-Dist: einx>=0.3.0
Requires-Dist: einops>=0.8.0
Requires-Dist: torch>=2.5
Provides-Extra: examples
Requires-Dist: local-attention>=1.11.2; extra == "examples"
Requires-Dist: simplicial-attention>=0.1.5; extra == "examples"
Requires-Dist: tqdm; extra == "examples"
Provides-Extra: test
Requires-Dist: pytest; extra == "test"
Dynamic: license-file
